CONTRIBUTING.rst
HISTORY.rst
LICENSE
MANIFEST.in
README.rst
resources.qrc
setup.py
./__init__.py
./clodsa.py
./labelStoma.py
data/predefined_classes.txt
fichs/vocEstomas.names
fichs/yolov3Estomas.cfg
labelStoma.egg-info/PKG-INFO
labelStoma.egg-info/SOURCES.txt
labelStoma.egg-info/dependency_links.txt
labelStoma.egg-info/entry_points.txt
labelStoma.egg-info/not-zip-safe
labelStoma.egg-info/requires.txt
labelStoma.egg-info/top_level.txt
libs/__init__.py
libs/canvas.py
libs/colorDialog.py
libs/constants.py
libs/excelDialog.py
libs/hashableQListWidgetItem.py
libs/labelDialog.py
libs/labelFile.py
libs/linea.py
libs/pascal_voc_io.py
libs/resources.py
libs/settings.py
libs/shape.py
libs/stomaExcel.py
libs/stringBundle.py
libs/toolBar.py
libs/ustr.py
libs/utils.py
libs/version.py
libs/yolo_io.py
libs/zoomWidget.py
notebooks/notebookYolo.py
predict/detect.py
predict/detectStoma.py
predict/generateExcelStoma.py
predict/selectPesos.py
resources/strings/strings-zh-CN.properties
resources/strings/strings-zh-TW.properties
resources/strings/strings.properties