Metadata-Version: 1.2
Name: labelStoma
Version: 1.5
Summary: labelStoma is a graphical tool for using and creating detection models
Home-page: https://github.com/ancasag/labelStoma
Author: Angela Casado
Author-email: angela.casado@unirioja.es
License: MIT license
Keywords: labelStoma detection deeplearning
Platform: UNKNOWN
Classifier: Development Status :: 5 - Production/Stable
Classifier: Intended Audience :: Developers
Classifier: License :: OSI Approved :: MIT License
Classifier: Natural Language :: English
Classifier: Programming Language :: Python :: 3
Classifier: Programming Language :: Python :: 3.3
Classifier: Programming Language :: Python :: 3.4
Classifier: Programming Language :: Python :: 3.5
Classifier: Programming Language :: Python :: 3.6
Classifier: Programming Language :: Python :: 3.7
Requires-Python: >=3.0.0
